{"paths":{},"types":[],"uuids":["1384c73f7","18008e1e9","1c3bfd326","1db4c3e80","1f88a2190","2dL3kvpAxJu6GJ7RdqJG5J","02delMVqdBD70a/HSD99FK","22ttlYsHJNYaJqj4HxSGJJ","2cteiVLA1BvYyWkBQUIhwU","3bPH/eVjpBwatZW95yiZ2g","48xGJhhExF+p0UqidTdlgH","4dy3bzAxtN27ePMT4K+n4J","4en8Ag9bBJerhdkfaYWrQf","67W5AxmZNMl4kTFmX2aC15","6dv7ChnmxJLK1qR/7wrX3N","70rXsy3GhCupAC7swBM3xw","78TIn2WZ5BrLNFDAIM5t8p","7bteRfy1VNM7WZ5TC5zxh3","822R4fz4JCdYMYhmVrPhl+","8fzgQg+m1Ch7E9qxIMoQZ9","9fY0JTzndH4YtBxHsY10DV","a2MjXRFdtLlYQ5ouAFv/+R","a5oPV/WpVM8Jil95iLrN8X","bdK2+C2a5Fi76BGeuDeTUI","caIYYCN7ZNuoKzDBxpWEGf","e5oxhVxdZOe7x6mt/5LzV0","e8x6aRFZdMD5H+EMw1J1lb","ecpdLyjvZBwrvm+cedCcQy","f98Sflw7xAo4/+ghCsPMPO"],"scenes":{"db://assets/Scene/main.fire":5},"redirect":[6,0,25,1,27,0],"deps":["internal","resources"],"packs":{"08cfe3f9e":[7,8,5,9,10,11,12,13,14,15,16,17,18,19,20,21,22,23,24,26,28],"0c03d9c66":[0,1,2,3,4]},"name":"main","importBase":"import","nativeBase":"native","debug":false,"isZip":false,"encrypted":false,"versions":{"import":["08cfe3f9e","20f45","0c03d9c66","eca8f"],"native":[0,"7fc85",1,"2df13",2,"20472",3,"5b35e",4,"ecc4c"]}}